README.md
setup.py
mailru_parser/__init__.py
mailru_parser/exceptions.py
mailru_parser/mailru.py
mailru_parser.egg-info/PKG-INFO
mailru_parser.egg-info/SOURCES.txt
mailru_parser.egg-info/dependency_links.txt
mailru_parser.egg-info/requires.txt
mailru_parser.egg-info/top_level.txt