Metadata-Version: 1.1
Name: mailru-parser
Version: 0.0.16
Summary: Parse html content of Mail.ru
Home-page: https://github.com/KokocGroup/mailru-parser
Author: UNKNOWN
Author-email: UNKNOWN
License: UNKNOWN
Download-URL: https://github.com/KokocGroup/mailru-parser/tarball/v0.0.16
Platform: UNKNOWN
